steamcheck/__init__.py
steamcheck/check.py
steamcheck/main.py
steamcheck-1.0.1.dist-info/LICENSE
steamcheck-1.0.1.dist-info/METADATA
steamcheck-1.0.1.dist-info/WHEEL
steamcheck-1.0.1.dist-info/entry_points.txt
steamcheck-1.0.1.dist-info/top_level.txt
steamcheck-1.0.1.dist-info/RECORD
