Metadata-Version: 2.1
Name: steamcheck
Version: 1.0.1
Summary: A command-line tool to check availability of lists of potential Steam IDs and Steam Groups
Home-page: https://github.com/checker/steamcheck
Author: CrocBuzz Studios
Author-email: alex@crocbuzzstudios.com
License: UNKNOWN
Platform: UNKNOWN
Classifier: Programming Language :: Python :: 3
Classifier: License :: OSI Approved :: GNU General Public License v3 (GPLv3)
Classifier: Operating System :: OS Independent
Requires-Python: >=3.7
